{
    "metadata": {
        "_created": "2013-02-21T15:32:46-05:00",
        "description": "BibJSON collection sample",
        "format": "BibJSON",
        "license": "some licence",
        "population": "cap",
        "query": "/publications?population=cap&changedSince=2012-10-25T01:35:57Z",
        "records": 2
    },
    "records": [
        {
            "identifer": [
                {
                    "id": "15262723",
                    "type": "PMID",
                    "url": "https://www.ncbi.nlm.nih.gov/pubmed/15262723"
                },
                {
                    "id": "",
                    "type": "WoSItemID",
                    "url": "https://ws.isiknowledge.com/cps/openurl/service?url_ver=Z39.88-2004&rft_id=info:ut/"
                },
                {
                    "id": "45435892",
                    "type": "PublicationItemID"
                },
                {
                    "id": "1573",
                    "type": "SULPubId",
                    "url": "https://sulcap.stanford.edu/publications/1573"
                }
            ],
            "title": "Use of a dual-mode erbium:YAG laser for the surgical correction of rhinophyma.",
            "abstract": "Rhinophyma is a cosmetically deforming disorder characterized by nodular hypertrophy of the nasal soft tissue. Treatment of rhinophyma usually consists of laser ablation or surgical excision for correction of the associated tissue deformity. We describe 6 patients with mild to severe rhinophyma who were treated with a dual-mode erbium:YAG (Er:YAG) laser, which provides the advantages of controlled ablative energy for tissue reduction and excellent intraoperative hemostasis. Outcome measures included patient satisfaction, clinician observer ratings, and an assessment of complications, including scarring, pigment abnormalities, and postoperative bleeding. All patients were satisfied with their outcomes, and no complications were detected during follow-up. All treatment outcomes were rated as very good to excellent at a 3-month follow-up visit. The flexibility of the dual-mode Er:YAG laser provides both controlled ablation and hemostasis, making it an ideal laser for the surgical treatment of rhinophyma.",
            "keywords": [],
            "author": [
                {
                    "name": "Fincher,Edgar,F"
                },
                {
                    "name": "Gladstone,Hayes,B"
                }
            ],
            "documenttypes": [
                "Journal Article"
            ],
            "category": "Journal Document",
            "timescited": "",
            "timesnotselfcited": "",
            "rank": "",
            "ordinalrank": "0",
            "normalizedrank": "",
            "newpublicationid": "",
            "isobsolete": "false",
            "publisher": "",
            "address": "",
            "mesh": [
                {
                    "descriptor": [
                        {
                            "major": "N",
                            "name": "Adult"
                        }
                    ]
                },
                {
                    "descriptor": [
                        {
                            "major": "N",
                            "name": "Aged"
                        }
                    ]
                },
                {
                    "descriptor": [
                        {
                            "major": "N",
                            "name": "Algorithms"
                        }
                    ]
                },
                {
                    "descriptor": [
                        {
                            "major": "N",
                            "name": "Female"
                        }
                    ]
                },
                {
                    "descriptor": [
                        {
                            "major": "N",
                            "name": "Humans"
                        }
                    ]
                },
                {
                    "descriptor": [
                        {
                            "major": "N",
                            "name": "Laser Therapy"
                        }
                    ],
                    "qualifier": [
                        {
                            "major": "Y",
                            "name": "methods"
                        }
                    ]
                },
                {
                    "descriptor": [
                        {
                            "major": "N",
                            "name": "Male"
                        }
                    ]
                },
                {
                    "descriptor": [
                        {
                            "major": "N",
                            "name": "Middle Aged"
                        }
                    ]
                },
                {
                    "descriptor": [
                        {
                            "major": "N",
                            "name": "Rhinophyma"
                        }
                    ],
                    "qualifier": [
                        {
                            "major": "Y",
                            "name": "surgery"
                        }
                    ]
                },
                {
                    "descriptor": [
                        {
                            "major": "N",
                            "name": "Treatment Outcome"
                        }
                    ]
                }
            ],
            "journal": {
                "name": "Archives of facial plastic surgery ",
                "volume": "6",
                "issue": "4",
                "pages": "267-271",
                "date": "2004-07-01T00:00:00",
                "year": "2004",
                "publicationimpactfactor": "",
                "subjectcategories": [],
                "identifer": [
                    {
                        "id": "1521-2491",
                        "type": "issn",
                        "url": "https://searchworks.stanford.edu/?search_field=advanced&number=1521-2491"
                    },
                    {
                        "id": "",
                        "type": "doi",
                        "url": "https://doi.org/"
                    }
                ],
                "conferencestartdate": "",
                "conferenceenddate": ""
            },
            "contributions": [
                {
                    "sul_author_id": 1573,
                    "cap_profile_id": 3845,
                    "status": "approved",
                    "highlight_ind": "0"
                }
            ],
            "chicago": "Fincher, Edgar F., and Hayes B. Gladstone. 2004. “Use of a Dual-Mode Erbium:YAG Laser For the Surgical Correction of Rhinophyma.”. <i>Archives of Facial Plastic Surgery </i> 6 (4).",
            "apa": "Fincher, E. F., &#38; Gladstone, H. B. (2004). Use of a dual-mode erbium:YAG laser for the surgical correction of rhinophyma. <i>Archives of facial plastic surgery </i>, <i>6</i>(4).",
            "mla": "Fincher, Edgar F., and Hayes B. Gladstone. “Use of a Dual-Mode Erbium:YAG Laser For the Surgical Correction of Rhinophyma.”. <i>Archives of facial plastic surgery </i> 6.4 (2004): n. pag. Print.",
            "lastupdated": "2013-02-20T20:41:39Z"
        },
        {
            "identifer": [
                {
                    "id": "15137956",
                    "type": "PMID",
                    "url": "https://www.ncbi.nlm.nih.gov/pubmed/15137956"
                },
                {
                    "id": "",
                    "type": "WoSItemID",
                    "url": "https://ws.isiknowledge.com/cps/openurl/service?url_ver=Z39.88-2004&rft_id=info:ut/"
                },
                {
                    "id": "45408384",
                    "type": "PublicationItemID"
                },
                {
                    "id": "1574",
                    "type": "SULPubId",
                    "url": "https://sulcap.stanford.edu/publications/1574"
                }
            ],
            "title": "The etiology and epidemiology of anal cancer.",
            "abstract": "The anatomic definitions for anal cancer (canal versus margin) are made based on the relationship of the tumor to the anal verge. This method had led to confusion for some providers. A modification in the terminology is proposed that includes intra-anal, perianal, and skin as categories. The cause of anal carcinoma remains to be fully elucidated, and HPV seems to play a central role in this process. The incidence of anal cancers has increased, which is related to the evolution of HIV and AIDS, and their treatment. The accurate pathologic analysis of anal tumors is complex and is significantly aided by close communication between clinician and pathologist.",
            "keywords": [],
            "author": [
                {
                    "name": "Welton,Mark,Lane"
                },
                {
                    "name": "Sharkey,Francis,E"
                },
                {
                    "name": "Kahlenberg,Morton,S"
                }
            ],
            "documenttypes": [
                "Journal Article",
                "Review"
            ],
            "category": "Journal Document",
            "timescited": "",
            "timesnotselfcited": "",
            "rank": "",
            "ordinalrank": "1",
            "normalizedrank": "",
            "newpublicationid": "",
            "isobsolete": "false",
            "publisher": "",
            "address": "",
            "mesh": [
                {
                    "descriptor": [
                        {
                            "major": "N",
                            "name": "Acquired Immunodeficiency Syndrome"
                        }
                    ],
                    "qualifier": [
                        {
                            "major": "N",
                            "name": "virology"
                        }
                    ]
                },
                {
                    "descriptor": [
                        {
                            "major": "N",
                            "name": "Adult"
                        }
                    ]
                },
                {
                    "descriptor": [
                        {
                            "major": "N",
                            "name": "Anal Canal"
                        }
                    ],
                    "qualifier": [
                        {
                            "major": "N",
                            "name": "pathology"
                        }
                    ]
                },
                {
                    "descriptor": [
                        {
                            "major": "N",
                            "name": "Anus Neoplasms"
                        }
                    ],
                    "qualifier": [
                        {
                            "major": "N",
                            "name": "epidemiology"
                        },
                        {
                            "major": "Y",
                            "name": "etiology"
                        },
                        {
                            "major": "N",
                            "name": "virology"
                        }
                    ]
                },
                {
                    "descriptor": [
                        {
                            "major": "N",
                            "name": "Carcinoma, Squamous Cell"
                        }
                    ],
                    "qualifier": [
                        {
                            "major": "N",
                            "name": "virology"
                        }
                    ]
                },
                {
                    "descriptor": [
                        {
                            "major": "N",
                            "name": "Female"
                        }
                    ]
                },
                {
                    "descriptor": [
                        {
                            "major": "N",
                            "name": "HIV Infections"
                        }
                    ],
                    "qualifier": [
                        {
                            "major": "N",
                            "name": "virology"
                        }
                    ]
                },
                {
                    "descriptor": [
                        {
                            "major": "N",
                            "name": "Humans"
                        }
                    ]
                },
                {
                    "descriptor": [
                        {
                            "major": "N",
                            "name": "Male"
                        }
                    ]
                },
                {
                    "descriptor": [
                        {
                            "major": "N",
                            "name": "Middle Aged"
                        }
                    ]
                },
                {
                    "descriptor": [
                        {
                            "major": "N",
                            "name": "Papillomaviridae"
                        }
                    ],
                    "qualifier": [
                        {
                            "major": "N",
                            "name": "physiology"
                        }
                    ]
                },
                {
                    "descriptor": [
                        {
                            "major": "N",
                            "name": "Papillomavirus Infections"
                        }
                    ],
                    "qualifier": [
                        {
                            "major": "N",
                            "name": "virology"
                        }
                    ]
                }
            ],
            "journal": {
                "name": "Surgical oncology clinics of North America",
                "volume": "13",
                "issue": "2",
                "pages": "263-275",
                "date": "2004-04-01T00:00:00",
                "year": "2004",
                "publicationimpactfactor": "",
                "subjectcategories": [],
                "identifer": [
                    {
                        "id": "1055-3207",
                        "type": "issn",
                        "url": "https://searchworks.stanford.edu/?search_field=advanced&number=1055-3207"
                    },
                    {
                        "id": "",
                        "type": "doi",
                        "url": "https://doi.org/"
                    }
                ],
                "conferencestartdate": "",
                "conferenceenddate": ""
            },
            "contributions": [
                {
                    "sul_author_id": 1574,
                    "cap_profile_id": 3835,
                    "status": "approved",
                    "highlight_ind": "1"
                }
            ],
            "chicago": "Welton, Mark Lane, Francis E. Sharkey, and Morton S. Kahlenberg. 2004. “The Etiology and Epidemiology of Anal Cancer.”. <i>Surgical Oncology Clinics of North America</i> 13 (2).",
            "apa": "Welton, M. L., Sharkey, F. E., &#38; Kahlenberg, M. S. (2004). The etiology and epidemiology of anal cancer. <i>Surgical oncology clinics of North America</i>, <i>13</i>(2).",
            "mla": "Welton, Mark Lane, Francis E. Sharkey, and Morton S. Kahlenberg. “The Etiology and Epidemiology of Anal Cancer.”. <i>Surgical oncology clinics of North America</i> 13.2 (2004): n. pag. Print.",
            "lastupdated": "2013-02-20T20:41:40Z"
        }
    ]
}
